labelme2coco/__init__.py
labelme2coco/cli.py
labelme2coco/labelme2coco.py
labelme2coco/utils.py
tests/__init__.py
tests/test_unit.py
labelme2coco-0.2.6.dist-info/LICENSE
labelme2coco-0.2.6.dist-info/METADATA
labelme2coco-0.2.6.dist-info/WHEEL
labelme2coco-0.2.6.dist-info/entry_points.txt
labelme2coco-0.2.6.dist-info/top_level.txt
labelme2coco-0.2.6.dist-info/RECORD
