Metadata-Version: 2.1
Name: labelme2coco
Version: 0.2.6
Summary: Convert labelme annotations into coco format in one step
Home-page: https://github.com/fcakyon/labelme2coco
Author: Fatih Cagatay Akyon
Author-email: 
Classifier: Programming Language :: Python :: 3
Classifier: License :: OSI Approved :: MIT License
Classifier: Operating System :: OS Independent
Requires-Python: >=3.7
License-File: LICENSE
Requires-Dist: sahi>=0.8.19
Requires-Dist: jsonschema>=2.6.0
